{
  "indexes": [
    {
      "collectionGroup": "incidents",
      "queryScope": "COLLECTION",
      "fields": [
        { "fieldPath": "status", "order": "ASCENDING" },
        { "fieldPath": "createdAt", "order": "DESCENDING" }
      ]
    },
    {
      "collectionGroup": "incidents",
      "queryScope": "COLLECTION",
      "fields": [
        { "fieldPath": "geohash", "order": "ASCENDING" },
        { "fieldPath": "createdAt", "order": "DESCENDING" }
      ]
    },
    {
      "collectionGroup": "chainMessages",
      "queryScope": "COLLECTION",
      "fields": [
        { "fieldPath": "chainId", "order": "ASCENDING" },
        { "fieldPath": "createdAt", "order": "DESCENDING" }
      ]
    },
    {
      "collectionGroup": "chainAlerts",
      "queryScope": "COLLECTION",
      "fields": [
        { "fieldPath": "chainId", "order": "ASCENDING" },
        { "fieldPath": "createdAt", "order": "DESCENDING" }
      ]
    },
    {
      "collectionGroup": "chainMembers",
      "queryScope": "COLLECTION",
      "fields": [
        { "fieldPath": "chainId", "order": "ASCENDING" },
        { "fieldPath": "addedAt", "order": "ASCENDING" }
      ]
    },
    {
      "collectionGroup": "activityLogs",
      "queryScope": "COLLECTION",
      "fields": [
        { "fieldPath": "uid", "order": "ASCENDING" },
        { "fieldPath": "createdAt", "order": "DESCENDING" }
      ]
    }
  ],
  "fieldOverrides": []
}
